mfcli/.env.example
mfcli/__init__.py
mfcli/alembic.ini
mfcli/main.py
mfcli/agents/__init__.py
mfcli/agents/controller/__init__.py
mfcli/agents/controller/agent.py
mfcli/agents/controller/config.yaml
mfcli/agents/controller/tools.py
mfcli/agents/tools/general.py
mfcli/alembic/env.py
mfcli/alembic/script.py.mako
mfcli/alembic/versions/6ccc0c7c397c_added_fields_to_pdf_parts_model.py
mfcli/alembic/versions/769019ef4870_added_gemini_file_path_to_pdf_part_model.py
mfcli/alembic/versions/7a2e3a779fdc_added_functional_block_and_component_.py
mfcli/alembic/versions/7d5adb2a47a7_added_pdf_parts_model.py
mfcli/alembic/versions/7fcb7d6a5836_init.py
mfcli/alembic/versions/e0f2b5765c72_added_cascade_delete_for_models_that_.py
mfcli/alembic/versions/f1234567890a_make_bom_description_nullable.py
mfcli/cli/__init__.py
mfcli/cli/dependencies.py
mfcli/cli/main.py
mfcli/client/__init__.py
mfcli/client/chroma_db.py
mfcli/client/docling.py
mfcli/client/gemini.py
mfcli/client/vector_db.py
mfcli/constants/__init__.py
mfcli/constants/base_enum.py
mfcli/constants/directory_names.py
mfcli/constants/file_types.py
mfcli/constants/gemini.py
mfcli/constants/openai.py
mfcli/constants/pipeline_run_status.py
mfcli/crud/__init__.py
mfcli/crud/file.py
mfcli/crud/functional_blocks.py
mfcli/crud/netlist.py
mfcli/crud/pipeline_run.py
mfcli/crud/project.py
mfcli/digikey/__init__.py
mfcli/digikey/digikey.py
mfcli/mcp/__init__.py
mfcli/mcp/mcp_instance.py
mfcli/mcp/server.py
mfcli/mcp/state_manager.py
mfcli/mcp/configs/cline_mcp_settings.json
mfcli/mcp/configs/mfcli.mcp.json
mfcli/mcp/tools/__init__.py
mfcli/mcp/tools/query_knowledgebase.py
mfcli/models/__init__.py
mfcli/models/base.py
mfcli/models/bom.py
mfcli/models/datasheet.py
mfcli/models/debug_setup.py
mfcli/models/file.py
mfcli/models/file_docket.py
mfcli/models/file_metadata.py
mfcli/models/functional_blocks.py
mfcli/models/llm_response.py
mfcli/models/mcu.py
mfcli/models/mcu_errata.py
mfcli/models/netlist.py
mfcli/models/pdf_parts.py
mfcli-0.2.12.dist-info/licenses/LICENSE
mfcli-0.2.12.dist-info/METADATA
mfcli-0.2.12.dist-info/WHEEL
mfcli-0.2.12.dist-info/entry_points.txt
mfcli-0.2.12.dist-info/top_level.txt
mfcli-0.2.12.dist-info/RECORD
