Metadata-Version: 2.4
Name: mfcli
Version: 0.2.12
Summary: AI-powered CLI for analyzing hardware engineering documents
Author: Multifactor AI
License: MIT
Project-URL: Homepage, https://github.com/MultifactorAI/multifactor-adk-backend
Project-URL: Repository, https://github.com/MultifactorAI/multifactor-adk-backend
Project-URL: Issues, https://github.com/MultifactorAI/multifactor-adk-backend/issues
Keywords: hardware,engineering,AI,MCP,RAG,electronics,schematic,BOM,datasheet
Classifier: Development Status :: 4 - Beta
Classifier: Intended Audience :: Developers
Classifier: Intended Audience :: Science/Research
Classifier: License :: OSI Approved :: MIT License
Classifier: Programming Language :: Python :: 3.12
Classifier: Topic :: Scientific/Engineering :: Electronic Design Automation (EDA)
Requires-Python: <3.13,>=3.12
License-File: LICENSE
Requires-Dist: google-adk
Requires-Dist: python-dotenv
Requires-Dist: fastapi
Requires-Dist: uvicorn
Requires-Dist: pandas
Requires-Dist: pyyaml
Requires-Dist: sqlalchemy
Requires-Dist: pydantic-settings==2.10.1
Requires-Dist: alembic
Requires-Dist: werkzeug
Requires-Dist: boto3
Requires-Dist: botocore
Requires-Dist: pydantic==2.11.9
Requires-Dist: protobuf
Requires-Dist: sqlmodel
Requires-Dist: requests
Requires-Dist: openai
Requires-Dist: langchain
Requires-Dist: langchain-text-splitters
Requires-Dist: tiktoken
Requires-Dist: chromadb==1.3.4
Requires-Dist: urllib3
Requires-Dist: playwright
Requires-Dist: pymupdf
Requires-Dist: fastmcp
Requires-Dist: docling
Requires-Dist: pytest-asyncio
Requires-Dist: pytest-mock
Requires-Dist: trio
Requires-Dist: pikepdf
Provides-Extra: dev
Requires-Dist: pytest; extra == "dev"
Requires-Dist: pyinstaller; extra == "dev"
Requires-Dist: build; extra == "dev"
Requires-Dist: twine; extra == "dev"
Dynamic: license-file
